cssfinder_backend_rust-0.1.1.dist-info/METADATA
cssfinder_backend_rust-0.1.1.dist-info/WHEEL
cssfinder_backend_rust-0.1.1.dist-info/license_files/LICENSE.md
cssfinder_backend_rust-0.1.1.dist-info/license_files/LICENSE.md
cssfinder_backend_rust/__init__.py
cssfinder_backend_rust/cssfinder_backend_rust.abi3.so
cssfinder_backend_rust-0.1.1.dist-info/RECORD
