Metadata-Version: 2.1
Name: cssfinder_backend_rust
Version: 0.1.1
Classifier: Programming Language :: Rust
Classifier: Programming Language :: Python :: Implementation :: CPython
Classifier: Programming Language :: Python :: Implementation :: PyPy
License-File: LICENSE.md
License-File: LICENSE.md
Summary: Implementation of CSSFinder backend using Rust.
Author: Krzysztof Wisniewski <argmaster.world@gmail.com>
Author-email: Krzysztof Wisniewski <argmaster.world@gmail.com>
Requires-Python: >=3.8
Project-URL: repository, https://github.com/argmaster/cssfinder_backend_rust
